aeraryum/__init__.py
aeraryum-0.1.0.dist-info/METADATA
aeraryum-0.1.0.dist-info/WHEEL
aeraryum-0.1.0.dist-info/RECORD
