Metadata-Version: 2.4
Name: aeraryum
Version: 0.1.0
Summary: Aeraryum: Open-source macro portfolio tools (coming soon)
License: MIT
Author: Aeraryum
Author-email: dev@aeraryum.com
Requires-Python: >=3.10,<4.0
Classifier: License :: OSI Approved :: MIT License
Classifier: Programming Language :: Python :: 3
Classifier: Programming Language :: Python :: 3.10
Classifier: Programming Language :: Python :: 3.11
Classifier: Programming Language :: Python :: 3.12
Classifier: Programming Language :: Python :: 3.13
Classifier: Programming Language :: Python :: 3.14
